{
  "function": {
    "weather": {
      "build": true,
      "providerPlugin": "awscloudformation",
      "service": "Lambda"
    },
    "myTestGrapQlFunc": {
      "build": true,
      "providerPlugin": "awscloudformation",
      "service": "Lambda",
      "dependsOn": []
    }
  },
  "api": {
    "weatherAPI": {
      "service": "API Gateway",
      "providerPlugin": "awscloudformation",
      "dependsOn": [
        {
          "category": "function",
          "resourceName": "weather",
          "attributes": [
            "Name",
            "Arn"
          ]
        }
      ]
    }
  },
  "hosting": {
    "amplifyhosting": {
      "service": "amplifyhosting",
      "type": "cicd",
      "lastPushTimeStamp": "2022-08-19T16:55:26.402Z"
    }
  }
}